modelrepo/__init__.py
modelrepo/factory.py
modelrepo/models/__init__.py
modelrepo/models/base.py
modelrepo/repository/__init__.py
modelrepo/repository/_in_memory_model_repository.py
modelrepo/repository/_model_repository.py
modelrepo/repository/_mongo_db_model_repository.py
modelrepo/repository/_sql_alchemy_model_repository.py
modelrepo-1.0.0.dist-info/METADATA
modelrepo-1.0.0.dist-info/WHEEL
modelrepo-1.0.0.dist-info/RECORD
