Metadata-Version: 2.3
Name: modelrepo
Version: 1.0.0
Summary: Python package for interacting with databases using model repositories.
Author: Noah Chalifour
Author-email: chalifournoah@gmail.com
Requires-Python: >=3.12,<4.0
Classifier: Programming Language :: Python :: 3
Classifier: Programming Language :: Python :: 3.12
Classifier: Programming Language :: Python :: 3.13
Requires-Dist: dependency-injector (>=4.48,<5.0)
Requires-Dist: mkdocs-api-autonav (>=0.3,<0.4)
Requires-Dist: mkdocs-material (>=9.6,<10.0)
Requires-Dist: mkdocstrings[python] (>=0.18)
Requires-Dist: pymongo (>=4.13,<5.0)
Requires-Dist: sqlalchemy (>=2.0,<3.0)
